AUTHORS
LICENSE
MANIFEST.in
README.md
pyproject.toml
src/opentaskpy/addons/winrm/__init__.py
src/opentaskpy/addons/winrm/remotehandlers/__init__.py
src/opentaskpy/addons/winrm/remotehandlers/auth.py
src/opentaskpy/addons/winrm/remotehandlers/winrm.py
src/opentaskpy/addons/winrm/remotehandlers/winrm_put_file.ps1
src/opentaskpy/addons/winrm/remotehandlers/schemas/execution/winrm/protocol.json
src/opentaskpy/addons/winrm/remotehandlers/schemas/execution/winrm/winrm.json
src/opentaskpy/addons/winrm/remotehandlers/schemas/transfer/winrm_destination.json
src/opentaskpy/addons/winrm/remotehandlers/schemas/transfer/winrm_source.json
src/opentaskpy/addons/winrm/remotehandlers/schemas/transfer/winrm_destination/protocol.json
src/opentaskpy/addons/winrm/remotehandlers/schemas/transfer/winrm_destination/rename.json
src/opentaskpy/addons/winrm/remotehandlers/schemas/transfer/winrm_source/conditionals.json
src/opentaskpy/addons/winrm/remotehandlers/schemas/transfer/winrm_source/fileWatch.json
src/opentaskpy/addons/winrm/remotehandlers/schemas/transfer/winrm_source/logWatch.json
src/opentaskpy/addons/winrm/remotehandlers/schemas/transfer/winrm_source/postCopyAction.json
src/opentaskpy/addons/winrm/remotehandlers/schemas/transfer/winrm_source/protocol.json
src/otf_addons_winrm.egg-info/PKG-INFO
src/otf_addons_winrm.egg-info/SOURCES.txt
src/otf_addons_winrm.egg-info/dependency_links.txt
src/otf_addons_winrm.egg-info/requires.txt
src/otf_addons_winrm.egg-info/top_level.txt
tests/test_taskhandler_execution_winrm.py
tests/test_taskhandler_transfer_winrm.py
tests/test_winrm_execution_schema_validate.py
tests/test_winrm_transfer_schema_validate.py