Metadata-Version: 2.4
Name: otf-addons-winrm
Version: 26.2.0
Summary: Addons for opentaskpy, giving it the ability to interact with Windows machines via WinRM.
Author-email: Adam McDonagh <adam@elitemonkey.net>
License: GPLv3
Project-URL: Homepage, https://github.com/adammcdonagh/otf-addons-winrm
Project-URL: Bug Tracker, https://github.com/adammcdonagh/otf-addons-winrm/issues
Project-URL: Changelog, https://github.com/adammcdonagh/otf-addons-winrm/blob/main/CHANGELOG.md
Keywords: automation,task,framework,windows,winrm,remote,otf
Classifier: Programming Language :: Python :: 3
Classifier: License :: OSI Approved :: GNU General Public License v3 (GPLv3)
Classifier: Operating System :: POSIX
Requires-Python: >=3.11
License-File: LICENSE
License-File: AUTHORS
Requires-Dist: pywinrm>=0.5.0
Requires-Dist: opentaskpy>=v24.19.0
Provides-Extra: dev
Requires-Dist: pytest-shell; extra == "dev"
Requires-Dist: types-requests; extra == "dev"
Requires-Dist: types-python-dateutil; extra == "dev"
Requires-Dist: black>=25.1.0; extra == "dev"
Requires-Dist: isort; extra == "dev"
Requires-Dist: pytest; extra == "dev"
Requires-Dist: bumpver; extra == "dev"
Requires-Dist: pytest-shell; extra == "dev"
Requires-Dist: pre-commit; extra == "dev"
Requires-Dist: pylint; extra == "dev"
Requires-Dist: pydantic; extra == "dev"
Requires-Dist: mypy; extra == "dev"
Requires-Dist: ruff; extra == "dev"
Requires-Dist: coverage; extra == "dev"
Requires-Dist: pytest-cov; extra == "dev"
Requires-Dist: freezegun; extra == "dev"
Requires-Dist: dotenv; extra == "dev"
Dynamic: license-file
